README.md
setup.py
NoIf/__init__.py
NoIf/base.py
NoIf.egg-info/PKG-INFO
NoIf.egg-info/SOURCES.txt
NoIf.egg-info/dependency_links.txt
NoIf.egg-info/top_level.txt