Metadata-Version: 2.1
Name: NoIf
Version: 0.3.0
Summary: No more if else code
Home-page: https://github.com/AngelovLee/NoIf
Author: Jansen Leo
Author-email: 2835347017@qq.com
Maintainer: Jansen Leo
Maintainer-email: 2835347017@qq.com
License: MIT License
Platform: linux
Platform: windows
Classifier: Development Status :: 4 - Beta
Classifier: Operating System :: OS Independent
Classifier: Intended Audience :: Developers
Classifier: License :: OSI Approved :: MIT License
Classifier: Programming Language :: Python
Classifier: Programming Language :: Python :: Implementation
Classifier: Programming Language :: Python :: 3.6
Classifier: Programming Language :: Python :: 3.7
Classifier: Programming Language :: Python :: 3.8
Classifier: Topic :: Software Development :: Libraries
